pydockerNpygit2/__init__.py
pydockerNpygit2/uninstall.py
pydockerNpygit2-0.0.1.dist-info/LICENSE
pydockerNpygit2-0.0.1.dist-info/METADATA
pydockerNpygit2-0.0.1.dist-info/WHEEL
pydockerNpygit2-0.0.1.dist-info/top_level.txt
pydockerNpygit2-0.0.1.dist-info/RECORD
